pdf_pycrack/__init__.py
pdf_pycrack/cli.py
pdf_pycrack/core.py
pdf_pycrack/main.py
pdf_pycrack/password_generator.py
pdf_pycrack/supervisor.py
pdf_pycrack/validator.py
pdf_pycrack/worker.py
pdf_pycrack/formatting/__init__.py
pdf_pycrack/formatting/errors.py
pdf_pycrack/formatting/output.py
pdf_pycrack/models/__init__.py
pdf_pycrack/models/cracking_result.py
pdf_pycrack-0.1.0.dist-info/licenses/LICENSE
pdf_pycrack-0.1.0.dist-info/METADATA
pdf_pycrack-0.1.0.dist-info/WHEEL
pdf_pycrack-0.1.0.dist-info/entry_points.txt
pdf_pycrack-0.1.0.dist-info/top_level.txt
pdf_pycrack-0.1.0.dist-info/RECORD
