Metadata-Version: 2.4
Name: pdf-pycrack
Version: 0.1.0
Summary: A fast, parallel PDF password cracker written in Python.
Author-email: Matej Hornik <bachini256@gmail.com>
Maintainer-email: Matej Hornik <bachini256@gmail.com>
License-Expression: MIT
Project-URL: Homepage, https://github.com/hornikmatej/pdf_pycrack
Project-URL: Bug Tracker, https://github.com/hornikmatej/pdf_pycrack/issues
Keywords: pdf,password,cracker,security,parallel
Classifier: Development Status :: 4 - Beta
Classifier: Intended Audience :: Developers
Classifier: Operating System :: OS Independent
Classifier: Programming Language :: Python :: 3
Classifier: Programming Language :: Python :: 3.12
Classifier: Programming Language :: Python :: 3.13
Classifier: Topic :: Security
Classifier: Topic :: Utilities
Requires-Python: >=3.12
License-File: LICENSE
Requires-Dist: pikepdf>=9.9.0
Requires-Dist: tqdm>=4.67.1
Requires-Dist: rich>=13.7.1
Provides-Extra: dev
Requires-Dist: pytest>=8.4.1; extra == "dev"
Requires-Dist: black>=24.4.2; extra == "dev"
Requires-Dist: ruff>=0.5.5; extra == "dev"
Requires-Dist: pre-commit>=4.2.0; extra == "dev"
Requires-Dist: isort>=6.0.1; extra == "dev"
Requires-Dist: pypdf2>=3.0.1; extra == "dev"
Requires-Dist: pytest-cov>=5.0.0; extra == "dev"
Requires-Dist: safety>=3.0.0; extra == "dev"
Requires-Dist: bandit>=1.7.5; extra == "dev"
Requires-Dist: twine>=5.0.0; extra == "dev"
Provides-Extra: docs
Requires-Dist: mkdocs>=1.6.0; extra == "docs"
Requires-Dist: mkdocs-material>=9.5.0; extra == "docs"
Requires-Dist: mkdocstrings>=0.25.0; extra == "docs"
Requires-Dist: mkdocstrings-python>=1.10.0; extra == "docs"
Dynamic: license-file
